{"id": 1, "title": "Fan", "industry": "Bollywood", "writer": "Manish Sherma, Habib Faisal", "director": "Manish Sherma", "storyline": "Gaurav a boy from Delhi is a die hard fan of Bollywood superstar Aryan Khanna. He comes to Mumbai to wish his idol on his Birthday, but over there things got worst and Gaurav's obsession turned himself a man who wants to create chaos in Aryan Khanna's life.", "country": "India", "languages": "Hindi", "genres": "Action, Drama, Thriller ", "budget": 15, "box_office_domestic": "", "box_office_gross": 28, "production_company": "Redchillies, Yash Raj", "rating": [0.0, 0], "run_time": "144"}